MANIFEST.in
README.md
setup.py
colabtweak/__init__.py
colabtweak/load_data_path.py
colabtweak.egg-info/PKG-INFO
colabtweak.egg-info/SOURCES.txt
colabtweak.egg-info/dependency_links.txt
colabtweak.egg-info/not-zip-safe
colabtweak.egg-info/requires.txt
colabtweak.egg-info/top_level.txt