Metadata-Version: 2.1
Name: colabtweak
Version: 0.1.0
Summary: Tweaks for Google Colab
Home-page: http://github.com/kmedian/colabtweak
Author: Ulf Hamster
Author-email: 554c46@gmail.com
License: MIT
Platform: UNKNOWN
Requires-Python: >=3.6
